LICENSE
README.md
pyproject.toml
setup.py
src/mathematic_package_willi1993.egg-info/PKG-INFO
src/mathematic_package_willi1993.egg-info/SOURCES.txt
src/mathematic_package_willi1993.egg-info/dependency_links.txt
src/mathematic_package_willi1993.egg-info/top_level.txt
src/mathematic_willi/__init__.py
src/mathematic_willi/aritmatika.py
src/mathematic_willi/bangun.py