Metadata-Version: 2.1
Name: mathematic-package-willi1993
Version: 1.1.0
Summary: Matematika untuk Python
Home-page: https://github.com/pypa/sampleproject
Author: Willi
Author-email: prajudiwilliam10@gmail.com 
License: UNKNOWN
Project-URL: Bug Tracker, https://github.com/pypa/sampleproject/issues
Platform: UNKNOWN
Classifier: Programming Language :: Python :: 3
Classifier: License :: OSI Approved :: MIT License
Classifier: Operating System :: OS Independent
Requires-Python: >=3.6
License-File: LICENSE
